Metadata-Version: 2.1
Name: fgaussbin-distributions
Version: 0.5
Summary: Gaussian and Binomial distributions
Home-page: UNKNOWN
Author: Francisca S dos Santos B
Author-email: fsoaresantos@gmail.com
License: UNKNOWN
Platform: UNKNOWN
